{"nodes": [{"id": "frontend_src_lib_db_js", "label": "db.js", "file_type": "code", "source_file": "frontend\\src\\lib\\db.js", "source_location": "L1"}, {"id": "db_salvadashdb", "label": "SalvaDashDB", "file_type": "code", "source_file": "frontend\\src\\lib\\db.js", "source_location": "L3"}, {"id": "db_salvadashdb_constructor", "label": ".constructor()", "file_type": "code", "source_file": "frontend\\src\\lib\\db.js", "source_location": "L7"}, {"id": "db_clearusercache", "label": "clearUserCache()", "file_type": "code", "source_file": "frontend\\src\\lib\\db.js", "source_location": "L18"}, {"id": "db_clearallcache", "label": "clearAllCache()", "file_type": "code", "source_file": "frontend\\src\\lib\\db.js", "source_location": "L23"}, {"id": "db_cacheentries", "label": "cacheEntries()", "file_type": "code", "source_file": "frontend\\src\\lib\\db.js", "source_location": "L29"}, {"id": "db_cacheaccounts", "label": "cacheAccounts()", "file_type": "code", "source_file": "frontend\\src\\lib\\db.js", "source_location": "L36"}, {"id": "db_cachedashboard", "label": "cacheDashboard()", "file_type": "code", "source_file": "frontend\\src\\lib\\db.js", "source_location": "L43"}, {"id": "db_getcacheddashboard", "label": "getCachedDashboard()", "file_type": "code", "source_file": "frontend\\src\\lib\\db.js", "source_location": "L51"}, {"id": "db_getcachedentries", "label": "getCachedEntries()", "file_type": "code", "source_file": "frontend\\src\\lib\\db.js", "source_location": "L62"}, {"id": "db_getcachedaccounts", "label": "getCachedAccounts()", "file_type": "code", "source_file": "frontend\\src\\lib\\db.js", "source_location": "L65"}], "edges": [{"source": "frontend_src_lib_db_js", "target": "dexie", "relation": "imports_from", "confidence": "EXTRACTED", "source_file": "frontend\\src\\lib\\db.js", "source_location": "L1", "weight": 1.0}, {"source": "frontend_src_lib_db_js", "target": "db_salvadashdb", "relation": "contains", "confidence": "EXTRACTED", "source_file": "frontend\\src\\lib\\db.js", "source_location": "L3", "weight": 1.0}, {"source": "db_salvadashdb", "target": "db_salvadashdb_constructor", "relation": "method", "confidence": "EXTRACTED", "source_file": "frontend\\src\\lib\\db.js", "source_location": "L7", "weight": 1.0}, {"source": "frontend_src_lib_db_js", "target": "db_clearusercache", "relation": "contains", "confidence": "EXTRACTED", "source_file": "frontend\\src\\lib\\db.js", "source_location": "L18", "weight": 1.0}, {"source": "frontend_src_lib_db_js", "target": "db_clearallcache", "relation": "contains", "confidence": "EXTRACTED", "source_file": "frontend\\src\\lib\\db.js", "source_location": "L23", "weight": 1.0}, {"source": "frontend_src_lib_db_js", "target": "db_cacheentries", "relation": "contains", "confidence": "EXTRACTED", "source_file": "frontend\\src\\lib\\db.js", "source_location": "L29", "weight": 1.0}, {"source": "frontend_src_lib_db_js", "target": "db_cacheaccounts", "relation": "contains", "confidence": "EXTRACTED", "source_file": "frontend\\src\\lib\\db.js", "source_location": "L36", "weight": 1.0}, {"source": "frontend_src_lib_db_js", "target": "db_cachedashboard", "relation": "contains", "confidence": "EXTRACTED", "source_file": "frontend\\src\\lib\\db.js", "source_location": "L43", "weight": 1.0}, {"source": "frontend_src_lib_db_js", "target": "db_getcacheddashboard", "relation": "contains", "confidence": "EXTRACTED", "source_file": "frontend\\src\\lib\\db.js", "source_location": "L51", "weight": 1.0}, {"source": "frontend_src_lib_db_js", "target": "db_getcachedentries", "relation": "contains", "confidence": "EXTRACTED", "source_file": "frontend\\src\\lib\\db.js", "source_location": "L62", "weight": 1.0}, {"source": "frontend_src_lib_db_js", "target": "db_getcachedaccounts", "relation": "contains", "confidence": "EXTRACTED", "source_file": "frontend\\src\\lib\\db.js", "source_location": "L65", "weight": 1.0}], "raw_calls": [{"caller_nid": "db_salvadashdb_constructor", "callee": "super", "source_file": "frontend\\src\\lib\\db.js", "source_location": "L8"}, {"caller_nid": "db_salvadashdb_constructor", "callee": "stores", "source_file": "frontend\\src\\lib\\db.js", "source_location": "L9"}, {"caller_nid": "db_salvadashdb_constructor", "callee": "version", "source_file": "frontend\\src\\lib\\db.js", "source_location": "L9"}, {"caller_nid": "db_clearusercache", "callee": "delete", "source_file": "frontend\\src\\lib\\db.js", "source_location": "L19"}, {"caller_nid": "db_clearusercache", "callee": "equals", "source_file": "frontend\\src\\lib\\db.js", "source_location": "L19"}, {"caller_nid": "db_clearusercache", "callee": "where", "source_file": "frontend\\src\\lib\\db.js", "source_location": "L19"}, {"caller_nid": "db_clearusercache", "callee": "delete", "source_file": "frontend\\src\\lib\\db.js", "source_location": "L20"}, {"caller_nid": "db_clearusercache", "callee": "equals", "source_file": "frontend\\src\\lib\\db.js", "source_location": "L20"}, {"caller_nid": "db_clearusercache", "callee": "where", "source_file": "frontend\\src\\lib\\db.js", "source_location": "L20"}, {"caller_nid": "db_clearusercache", "callee": "delete", "source_file": "frontend\\src\\lib\\db.js", "source_location": "L21"}, {"caller_nid": "db_clearusercache", "callee": "equals", "source_file": "frontend\\src\\lib\\db.js", "source_location": "L21"}, {"caller_nid": "db_clearusercache", "callee": "where", "source_file": "frontend\\src\\lib\\db.js", "source_location": "L21"}, {"caller_nid": "db_clearallcache", "callee": "clear", "source_file": "frontend\\src\\lib\\db.js", "source_location": "L24"}, {"caller_nid": "db_clearallcache", "callee": "clear", "source_file": "frontend\\src\\lib\\db.js", "source_location": "L25"}, {"caller_nid": "db_clearallcache", "callee": "clear", "source_file": "frontend\\src\\lib\\db.js", "source_location": "L26"}, {"caller_nid": "db_cacheentries", "callee": "now", "source_file": "frontend\\src\\lib\\db.js", "source_location": "L30"}, {"caller_nid": "db_cacheentries", "callee": "transaction", "source_file": "frontend\\src\\lib\\db.js", "source_location": "L31"}, {"caller_nid": "db_cacheaccounts", "callee": "now", "source_file": "frontend\\src\\lib\\db.js", "source_location": "L37"}, {"caller_nid": "db_cacheaccounts", "callee": "transaction", "source_file": "frontend\\src\\lib\\db.js", "source_location": "L38"}, {"caller_nid": "db_cachedashboard", "callee": "put", "source_file": "frontend\\src\\lib\\db.js", "source_location": "L44"}, {"caller_nid": "db_cachedashboard", "callee": "stringify", "source_file": "frontend\\src\\lib\\db.js", "source_location": "L47"}, {"caller_nid": "db_cachedashboard", "callee": "now", "source_file": "frontend\\src\\lib\\db.js", "source_location": "L48"}, {"caller_nid": "db_getcacheddashboard", "callee": "get", "source_file": "frontend\\src\\lib\\db.js", "source_location": "L52"}, {"caller_nid": "db_getcacheddashboard", "callee": "parse", "source_file": "frontend\\src\\lib\\db.js", "source_location": "L56"}, {"caller_nid": "db_getcachedentries", "callee": "sortBy", "source_file": "frontend\\src\\lib\\db.js", "source_location": "L63"}, {"caller_nid": "db_getcachedentries", "callee": "reverse", "source_file": "frontend\\src\\lib\\db.js", "source_location": "L63"}, {"caller_nid": "db_getcachedentries", "callee": "equals", "source_file": "frontend\\src\\lib\\db.js", "source_location": "L63"}, {"caller_nid": "db_getcachedentries", "callee": "where", "source_file": "frontend\\src\\lib\\db.js", "source_location": "L63"}, {"caller_nid": "db_getcachedaccounts", "callee": "sortBy", "source_file": "frontend\\src\\lib\\db.js", "source_location": "L66"}, {"caller_nid": "db_getcachedaccounts", "callee": "equals", "source_file": "frontend\\src\\lib\\db.js", "source_location": "L66"}, {"caller_nid": "db_getcachedaccounts", "callee": "where", "source_file": "frontend\\src\\lib\\db.js", "source_location": "L66"}]}